src/__init__.py
nahcrofDB-2.4.2.dist-info/LICENCE
nahcrofDB-2.4.2.dist-info/METADATA
nahcrofDB-2.4.2.dist-info/WHEEL
nahcrofDB-2.4.2.dist-info/top_level.txt
nahcrofDB-2.4.2.dist-info/RECORD
