Metadata-Version: 2.1
Name: nahcrofDB
Version: 2.4.2
Summary: A key-value database
Author: Tyrae Paul
Author-email: support@nahcrof.com
Keywords: database
Classifier: Development Status :: 5 - Production/Stable
Classifier: Intended Audience :: Developers
Classifier: Programming Language :: Python :: 3
License-File: LICENCE
